[
    {
        "idPost": "1567320386546589696",
        "urlPost": "pic.x.com/qRY7ltRkV0",
        "content": "https://t.co/qRY7ltRkV0",
        "like_count": 136761,
        "comment_count": 16502,
        "mediaUrl": [
            "https://pbs.twimg.com/media/FcA9Py7XgAAohg-.jpg"
        ]
    },
    {
        "idPost": "1470547831434153984",
        "urlPost": "pic.x.com/j7EuZcZqnh",
        "content": "https://t.co/j7EuZcZqnh",
        "like_count": 64534,
        "comment_count": 3055,
        "mediaUrl": [
            "https://pbs.twimg.com/media/FGhvcn9WYAIvntg.jpg",
            "https://pbs.twimg.com/media/FGhvcoAXwAIjEmY.jpg"
        ]
    },
    {
        "idPost": "1467954498085789696",
        "urlPost": "pic.x.com/SbFar4nqu9",
        "content": "“Virgil was here” https://t.co/SbFar4nqu9",
        "like_count": 71564,
        "comment_count": 895,
        "mediaUrl": [
            "https://pbs.twimg.com/media/FF8qbVRXEAoptDA.jpg"
        ]
    },
    {
        "idPost": "1467939930525548553",
        "urlPost": "pic.x.com/oElpGUJB76",
        "content": "✨ @jaden https://t.co/oElpGUJB76",
        "like_count": 49634,
        "comment_count": 849,
        "mediaUrl": [
            "https://pbs.twimg.com/media/FF8rVkpXEBAOx6Y.jpg"
        ]
    },
    {
        "idPost": "1467938615225368588",
        "urlPost": "pic.x.com/NStXwvWiDb",
        "content": "🐻 @drewhouse https://t.co/NStXwvWiDb",
        "like_count": 26292,
        "comment_count": 763,
        "mediaUrl": [
            "https://pbs.twimg.com/media/FF8qUAaWQAQZg0o.jpg",
            "https://pbs.twimg.com/media/FF8qUAZWYAQchgZ.jpg",
            "https://pbs.twimg.com/media/FF8qUAYXoAM5OKJ.jpg"
        ]
    },
    {
        "idPost": "1467177867377315840",
        "urlPost": "pic.x.com/uuudLUW0z8",
        "content": "Watch me perform at The 23rd Annual A Home for the Holidays at @thegrovela this Sunday at 9:30PM ET/9:00PM PT on @CBS  #Home4Holidays https://t.co/uuudLUW0z8",
        "like_count": 40055,
        "comment_count": 1235,
        "mediaUrl": [
            "https://pbs.twimg.com/media/FFx2b7IWUAUnwU0.jpg",
            "https://pbs.twimg.com/media/FFx2b7JXEAYQ-O6.jpg",
            "https://pbs.twimg.com/media/FFx2b7cXsAYNBIC.jpg"
        ]
    },
    {
        "idPost": "1466240586487406596",
        "urlPost": "pic.x.com/rdka1pH1Ew",
        "content": "I luv u📷: @rorykramer https://t.co/rdka1pH1Ew",
        "like_count": 61156,
        "comment_count": 1884,
        "mediaUrl": [
            "https://pbs.twimg.com/media/FFkh9d5XwAIf7p6.jpg",
            "https://pbs.twimg.com/media/FFkh9d3WYAMHL2R.jpg",
            "https://pbs.twimg.com/media/FFkh9d3XEAQvm19.jpg"
        ]
    },
    {
        "idPost": "1465396378704793602",
        "urlPost": "pic.x.com/Pw9beGolcE",
        "content": "We lost a real one, rest in paradise king. @virgilabloh ❤️ https://t.co/Pw9beGolcE",
        "like_count": 43311,
        "comment_count": 603,
        "mediaUrl": [
            "https://pbs.twimg.com/media/FFYiC83X0AEj9uI.jpg"
        ]
    },
    {
        "idPost": "1463661337851142148",
        "urlPost": "pic.x.com/puDKtkfauJ",
        "content": ".@drewhouse https://t.co/puDKtkfauJ",
        "like_count": 18394,
        "comment_count": 612,
        "mediaUrl": [
            "https://pbs.twimg.com/media/FE_4MOYXwAIJ1Mt.jpg"
        ]
    }
]