[
    {
        "idPost": "1791862248849174556",
        "urlPost": "pic.x.com/4mDhYptVZZ",
        "content": "Check out our client Memecoin! It's the perfect blend of creativity and awesomeness. Get ready to be amazed!💥📷#doge #investment #nft #binance #shitcoin #cryptoworld #shibainu #cryptocurrencies #meme #blockchaintechnology #eth #cryptomarket #hodl #bitcointrading #cryptomemes https://t.co/4mDhYptVZZ",
        "like_count": 15,
        "comment_count": 7,
        "mediaUrl": [
            "https://pbs.twimg.com/media/GN34vSGXsAIbI2z.jpg"
        ]
    },
    {
        "idPost": "1719411091057594827",
        "urlPost": "pic.x.com/ehi0yTJNFc",
        "content": "🎨 Just completed a stunning Animation for Client @lurxggs 🚀🌟Reach out to me with your projects, big or small 🌟💫 Let's bring your creative visions to life!  📩🔥#twitchstreamer #VTUBER #NVTUBERS #Smallstreamers #Youtubechannels #twitch #art #TwitchAffilate #PNGtubers https://t.co/ehi0yTJNFc",
        "like_count": 17,
        "comment_count": 13,
        "mediaUrl": [
            "https://pbs.twimg.com/ext_tw_video_thumb/1719410254075842560/pu/img/A08I2GSmhu1rQvoc.jpg"
        ]
    },
    {
        "idPost": "1837222269715644451",
        "urlPost": "pic.x.com/atlX5BPQYO",
        "content": "Recently did this amazing PFP/Banner for my satisfied client@iamihatemondays If you want some cool art like these DM me💥 https://t.co/atlX5BPQYO",
        "like_count": 66,
        "comment_count": 7,
        "mediaUrl": [
            "https://pbs.twimg.com/media/GX8fdNyXMAAM4yO.jpg",
            "https://pbs.twimg.com/media/GX8fe-JXQAA4HkN.jpg"
        ]
    },
    {
        "idPost": "1820489372703379835",
        "urlPost": "pic.x.com/Zw2EwT2nIW",
        "content": "Thank you so much@OsquieMusic for consideration, people contact here for Dope quality design work🤩 https://t.co/Zw2EwT2nIW",
        "like_count": 20,
        "comment_count": 2,
        "mediaUrl": [
            "https://pbs.twimg.com/media/GUOtU_7awAAvi6D.jpg",
            "https://pbs.twimg.com/media/GUOtV9PbQAAgHaA.jpg"
        ]
    },
    {
        "idPost": "1753659432138142145",
        "urlPost": "pic.x.com/x7kYIx0xe5",
        "content": "Another work done for my close client thank for trusting in me😍@Blvck_Spider for the consideration, people contact here for Dope quality Designing work   #graphicdesign #needoverlay #needanimation #needemotes #tattoodesign #bookcovers #needlogo #graphicsdesign #TwitterArt https://t.co/x7kYIx0xe5",
        "like_count": 14,
        "comment_count": 5,
        "mediaUrl": [
            "https://pbs.twimg.com/media/GFY_7ysaUAArRRK.jpg"
        ]
    },
    {
        "idPost": "1727189031946240021",
        "urlPost": "pic.x.com/kE1FkXXdr4",
        "content": "I created this amazing PFP design work for @SupremeWryIf you need amazing PFP or any graphic-related stuff, please hit me up.#twitchtv #twitchstreamer #twitchaffiliate #Kickstarter #illustration #pokemonarts #fanart #gamingcommunity #streamer #streamergirl #Live2D #fanart https://t.co/kE1FkXXdr4",
        "like_count": 13,
        "comment_count": 5,
        "mediaUrl": [
            "https://pbs.twimg.com/media/F_g0VcebEAAxCIO.jpg"
        ]
    },
    {
        "idPost": "1798292131280310419",
        "urlPost": "pic.x.com/KXSnQtHgug",
        "content": "I recently created this thumbnail for my happy client❤️❤️Open Commissions, Interested contact me.  . If you want some awesome merch design like this, DM me.    #Nft #TwitchEmotes #GraphicDesigner #digitalillustration #twitch #emotes #GraphicDesign #thumbnail #needemotes https://t.co/KXSnQtHgug",
        "like_count": 16,
        "comment_count": 5,
        "mediaUrl": [
            "https://pbs.twimg.com/media/GPTRAkuWUAAk_tm.jpg",
            "https://pbs.twimg.com/media/GPTRBeZXcAAUaJt.jpg",
            "https://pbs.twimg.com/media/GPTRCS9W0AAPNzm.jpg"
        ]
    },
    {
        "idPost": "1699872499687968994",
        "urlPost": "pic.x.com/5ff6YVNFkv",
        "content": "Hey Everyone! Recently made this logo and overlay screen for@ArianghGhIf you want yours, Let Me Know! https://t.co/5ff6YVNFkv",
        "like_count": 13,
        "comment_count": 5,
        "mediaUrl": [
            "https://pbs.twimg.com/media/F5co-a4bUAA8CF0.jpg",
            "https://pbs.twimg.com/media/F5cpAxBbUAE_1_X.jpg",
            "https://pbs.twimg.com/media/F5cpAw_bUAEEkI2.jpg"
        ]
    },
    {
        "idPost": "1818706277780144217",
        "urlPost": "pic.x.com/gKNDJ7dOQG",
        "content": "Thank you once again for trusting my work @ForeverForwardd I really enjoy working with you. I hope we work together again🥰 https://t.co/gKNDJ7dOQG",
        "like_count": 15,
        "comment_count": 0,
        "mediaUrl": [
            "https://pbs.twimg.com/ext_tw_video_thumb/1818706244582227970/pu/img/rTzOqS_nw0X27-Xf.jpg"
        ]
    },
    {
        "idPost": "1753658252796240166",
        "urlPost": "pic.x.com/AcBxZLRsSR",
        "content": "Did this amazing emotes for my man @AnthoneyMoya If any one need dope and fantastic emote HMU with the details https://t.co/AcBxZLRsSR",
        "like_count": 10,
        "comment_count": 4,
        "mediaUrl": [
            "https://pbs.twimg.com/media/GFY-wnUaQAAdyeS.jpg"
        ]
    },
    {
        "idPost": "1753654532410843236",
        "urlPost": "pic.x.com/kJnQgkvbDn",
        "content": "I recently created this thumbnail for my happy client @MrPutUpEasyOpen Commissions, Interested contact me.  . If you want some awesome merch design like this, DM me.    #TwitchEmotes #GraphicDesigner #digitalillustration #twitch #emotes #GraphicDesign #thumbnail #needemotes https://t.co/kJnQgkvbDn",
        "like_count": 12,
        "comment_count": 5,
        "mediaUrl": [
            "https://pbs.twimg.com/media/GFY7VrebkAAFGhu.jpg"
        ]
    },
    {
        "idPost": "1815462466643697759",
        "urlPost": "pic.x.com/PRwrRFe8FZ",
        "content": "Check out our client mascot logo! It's the perfect blend of creativity and awesomeness. Get ready to be amazed! 💥📷 https://t.co/PRwrRFe8FZ",
        "like_count": 14,
        "comment_count": 1,
        "mediaUrl": [
            "https://pbs.twimg.com/media/GTHRc8ObcAIFgSL.jpg"
        ]
    },
    {
        "idPost": "1759975960776990926",
        "urlPost": "pic.x.com/9UoqzxjMa5",
        "content": "Prepare to be amazed by these jaw-dropping money emotes I created for one of my favorite client @cashfn3.💸💰 https://t.co/9UoqzxjMa5",
        "like_count": 7,
        "comment_count": 5,
        "mediaUrl": [
            "https://pbs.twimg.com/media/GGywKxkXsAEEt7p.jpg",
            "https://pbs.twimg.com/media/GGywM6nXsAEDQmH.jpg",
            "https://pbs.twimg.com/media/GGywO9FW4AAMzDA.jpg",
            "https://pbs.twimg.com/media/GGywnchWAAAWa9d.jpg"
        ]
    },
    {
        "idPost": "1758870137032122557",
        "urlPost": "pic.x.com/NKKpsBKKuo",
        "content": "Introducing our awesome client @avawwe_ illustration! Thank you for your trust and I hope we work together in the future aswell.🥰 https://t.co/NKKpsBKKuo",
        "like_count": 6,
        "comment_count": 3,
        "mediaUrl": [
            "https://pbs.twimg.com/media/GGjB5gKW4AA6aon.jpg"
        ]
    },
    {
        "idPost": "1735748777682801022",
        "urlPost": "pic.x.com/w5XZWjdEGS",
        "content": "MASCOT COMMISSION FOR@thefootyarena  SO MUCH HAPPY WORKING WITH YOU AGAIN. 🔥 💖#graphicdesign #illustration #Illustrator #gfx #artists #Twitch #Streamers #Kick #affiliate #gamers #GameFi #overlays #logo #banner #logos #stream #alerts #looking #for #panels #art #cartoon https://t.co/w5XZWjdEGS",
        "like_count": 6,
        "comment_count": 7,
        "mediaUrl": [
            "https://pbs.twimg.com/media/GBad7SPaEAAKl61.jpg"
        ]
    },
    {
        "idPost": "1732290535094984724",
        "urlPost": "pic.x.com/O4JXv09Jil",
        "content": "Did this amazing emote for my man@AnthoneyMoyaIf you need amazing graphic-related stuff, please hit me up📷#twitchstreamer #twitchaffiliate #twitchemotes #GraphicDesigner #GraphicDesign #needemotesEMOTES https://t.co/O4JXv09Jil",
        "like_count": 4,
        "comment_count": 4,
        "mediaUrl": [
            "https://pbs.twimg.com/media/GApVC6KasAA45zD.jpg"
        ]
    },
    {
        "idPost": "1732291306498748558",
        "urlPost": "pic.x.com/LZBvmjcoFS",
        "content": "Did this amazing emote for my man@AnthoneyMoyaIf you need amazing graphic-related stuff, please hit me up📷 #twitchstreamer #twitchaffiliate #twitchemotes #GraphicDesigner #GraphicDesign #needemotesEMOTES https://t.co/LZBvmjcoFS",
        "like_count": 3,
        "comment_count": 6,
        "mediaUrl": [
            "https://pbs.twimg.com/media/GApVvevb0AAX8D1.jpg",
            "https://pbs.twimg.com/media/GApVv8casAAK9bD.jpg"
        ]
    },
    {
        "idPost": "1725218645846970621",
        "urlPost": "pic.x.com/eej6oc9UJr",
        "content": "Did this amazing Pfp/Logo for my man @OnlyMain_ 🔥Do check out his amazing channel https://t.co/6VEEfXuXvP https://t.co/eej6oc9UJr",
        "like_count": 4,
        "comment_count": 0,
        "mediaUrl": [
            "https://pbs.twimg.com/media/F_E1NsobAAAttsj.jpg"
        ]
    },
    {
        "idPost": "1487070291444609029",
        "urlPost": "pic.x.com/byUNIvnKUK",
        "content": "Let's grow together!!1. RetweetUniversal recycling symbol2. Comment your YT/TwitchMovie camera#SmallStreamersConnect#SupportSmallStreamers #Twitchstream #TwitchFam @SupStreamers#twitchtv #SupportSmallStreams #SmallYouTubeArmy #twitchcommunity #logo #GFX #Twitch https://t.co/byUNIvnKUK",
        "like_count": 8,
        "comment_count": 2,
        "mediaUrl": [
            "https://pbs.twimg.com/media/FKMijF9WYAEsROo.jpg"
        ]
    },
    {
        "idPost": "1505304607437864961",
        "urlPost": "pic.x.com/HWHTsAGCQq",
        "content": "Hiyas! Tattoo design done for my client if you are looking for tattoo designs as well hmu at my DM @diaryofkshuana ♥️ #needgraphicdesigner#needoverlay  #needanimation #needyoutubeintro #needemotes  #needNFT #tattoodesign https://t.co/HWHTsAGCQq",
        "like_count": 7,
        "comment_count": 0,
        "mediaUrl": [
            "https://pbs.twimg.com/media/FOPqkAXXwAIEoEB.jpg"
        ]
    },
    {
        "idPost": "1497506431142330374",
        "urlPost": "pic.x.com/QXWPIaC0cg",
        "content": "Does anybody need caricature? I'm here for you to serve best kindly HMU!!#needgraphicdesigner#needoverlay  #needanimation #needyoutubeintro #needemotes  #needNFT #SmallStreamersConnect#SupportSmallStreams#SupportSmallStreamers#100DaysOfCode@BlazedRTs https://t.co/QXWPIaC0cg",
        "like_count": 6,
        "comment_count": 0,
        "mediaUrl": [
            "https://pbs.twimg.com/media/FMg2KYVXsAAjLVO.jpg"
        ]
    },
    {
        "idPost": "1471121634249494529",
        "urlPost": "pic.x.com/FQWQeX47JB",
        "content": "#needlogo #needgraphicdesigner#needoverlay  #needanimation #needyoutubeintro #needemotes  #needNFT #SmallStreamersConnect#SupportSmallStreams#SupportSmallStreamers#100DaysOfCode@BlazedRTs@sme_rt@PromoteAMGamers https://t.co/FQWQeX47JB",
        "like_count": 6,
        "comment_count": 0,
        "mediaUrl": [
            "https://pbs.twimg.com/media/FGp5VEWWYAAN6m8.jpg"
        ]
    },
    {
        "idPost": "1661231607964135424",
        "urlPost": "pic.x.com/3HIWeQgPlU",
        "content": "Recently did this logo and banner for my satisfied client @sportslaydown If you want some cool art like these DM me.#logodesigns #bannerdesigns #GraphicDesigner #digitalillustration #artwork https://t.co/3HIWeQgPlU",
        "like_count": 1,
        "comment_count": 0,
        "mediaUrl": [
            "https://pbs.twimg.com/media/Fw3Zqn5akAE7upR.jpg",
            "https://pbs.twimg.com/media/Fw3ZsaLaYAAb4r0.jpg",
            "https://pbs.twimg.com/media/Fw3ZtJ0aIAEjHS3.jpg"
        ]
    },
    {
        "idPost": "1500119678517223437",
        "urlPost": "pic.x.com/5f0z2U1sle",
        "content": "Does anybody need mascot? I'm here for you to serve best kindly HMU!!#needgraphicdesigner#needoverlay  #needanimation #needyoutubeintro #needemotes  #needNFT #SmallStreamersConnect#SupportSmallStreams#SupportSmallStreamers#100DaysOfCode@BlazedRTs https://t.co/5f0z2U1sle",
        "like_count": 4,
        "comment_count": 0,
        "mediaUrl": [
            "https://pbs.twimg.com/media/FNF-5bOX0AMBW7G.jpg"
        ]
    },
    {
        "idPost": "1812134465621369342",
        "urlPost": "pic.x.com/jhiyMvlVrT",
        "content": "Recently did this amazing banner/header for my satisfied client @MistyEsports If you want some cool art like these DM me.💥 https://t.co/jhiyMvlVrT",
        "like_count": 5,
        "comment_count": 0,
        "mediaUrl": [
            "https://pbs.twimg.com/media/GSX-aZCWAAA-tmG.jpg"
        ]
    },
    {
        "idPost": "1497506307053854724",
        "urlPost": "pic.x.com/qoZ25HaLPL",
        "content": "Does anybody need overlay? I'm here for you to serve best kindly HMU!!#needgraphicdesigner#needoverlay  #needanimation #needyoutubeintro #needemotes  #needNFT #SmallStreamersConnect#SupportSmallStreams#SupportSmallStreamers#100DaysOfCode@BlazedRTs https://t.co/qoZ25HaLPL",
        "like_count": 4,
        "comment_count": 0,
        "mediaUrl": [
            "https://pbs.twimg.com/media/FMg2DLVWYAI031S.jpg"
        ]
    },
    {
        "idPost": "1497506115407339520",
        "urlPost": "pic.x.com/150pJdkCNS",
        "content": "Does anybody need banner? I'm here for you to serve best kindly HMU!!#needgraphicdesigner#needoverlay  #needanimation #needyoutubeintro #needemotes  #needNFT #SmallStreamersConnect#SupportSmallStreams#SupportSmallStreamers#100DaysOfCode@BlazedRTs https://t.co/150pJdkCNS",
        "like_count": 3,
        "comment_count": 0,
        "mediaUrl": [
            "https://pbs.twimg.com/media/FMg14BAXMAEu2ie.jpg"
        ]
    },
    {
        "idPost": "1749647286001668383",
        "urlPost": "pic.x.com/z5HXfgUgxr",
        "content": "Good Morning 💖🌅 https://t.co/z5HXfgUgxr",
        "like_count": 5,
        "comment_count": 1,
        "mediaUrl": [
            "https://pbs.twimg.com/media/GEf-1XsagAAPLZ3.jpg"
        ]
    },
    {
        "idPost": "1487070089711132673",
        "urlPost": "pic.x.com/nROhW7TV0f",
        "content": "Let's grow together!!1. RetweetUniversal recycling symbol2. Comment your YT/TwitchMovie camera#SmallStreamersConnect#SupportSmallStreamers #Twitchstream #TwitchFam @SupStreamers#twitchtv #SupportSmallStreams #SmallYouTubeArmy #twitchcommunity #logo #GFX #Twitch https://t.co/nROhW7TV0f",
        "like_count": 5,
        "comment_count": 0,
        "mediaUrl": [
            "https://pbs.twimg.com/media/FKMiXX7WQAIwujB.jpg"
        ]
    },
    {
        "idPost": "1487070255520301057",
        "urlPost": "pic.x.com/8JRS9kBD8H",
        "content": "Let's grow together!!1. RetweetUniversal recycling symbol2. Comment your YT/TwitchMovie camera#SmallStreamersConnect#SupportSmallStreamers #Twitchstream #TwitchFam @SupStreamers#twitchtv #SupportSmallStreams #SmallYouTubeArmy #twitchcommunity #logo #GFX #Twitch https://t.co/8JRS9kBD8H",
        "like_count": 5,
        "comment_count": 0,
        "mediaUrl": [
            "https://pbs.twimg.com/media/FKMihCJXoAUrNpK.jpg"
        ]
    },
    {
        "idPost": "1495792177435357189",
        "urlPost": "pic.x.com/l8i7dLG2mR",
        "content": "Does anybody need logo? I'm here for you to serve best kindly HMU!!#needgraphicdesigner#needoverlay  #needanimation #needyoutubeintro #needemotes  #needNFT #SmallStreamersConnect#SupportSmallStreams#SupportSmallStreamers#100DaysOfCode@BlazedRTs https://t.co/AsVQPMvKIS https://t.co/l8i7dLG2mR",
        "like_count": 2,
        "comment_count": 0,
        "mediaUrl": [
            "https://pbs.twimg.com/media/FMIfDtcXEAQHelM.jpg",
            "https://pbs.twimg.com/media/FLAH1haX0AE-bJP.jpg"
        ]
    },
    {
        "idPost": "1561786825030733830",
        "urlPost": "pic.x.com/KB8Fiznn98",
        "content": "Character design done for a client 😍@LordAzriel2. If anyone need this kind of work HMU.#OC #ocart #digitalart #DigitalArtist #digitaldrawing #drawing #Artist #artph #arttwt #artistontwittter #arthair https://t.co/KB8Fiznn98",
        "like_count": 3,
        "comment_count": 0,
        "mediaUrl": [
            "https://pbs.twimg.com/media/FayULTqWYAoqOtJ.jpg",
            "https://pbs.twimg.com/media/FayUXYCXwAI9y15.jpg"
        ]
    },
    {
        "idPost": "1611809978201034752",
        "urlPost": "pic.x.com/qHV5Xu9VlL",
        "content": "Hi everyone,Recently did this Logo for one of my satisfied client @Chief_Suave so if anyone needs any Graphic related work feel free to HMu with your concept.#logo #design #graphicdesign #branding #logodesigner #art #logodesigns #graphicdesigner #designer #logodesign #logos https://t.co/qHV5Xu9VlL",
        "like_count": 2,
        "comment_count": 0,
        "mediaUrl": [
            "https://pbs.twimg.com/media/Fl5I-MqaYAAExyK.jpg"
        ]
    },
    {
        "idPost": "1487070209043316740",
        "urlPost": "pic.x.com/tyvveSfx2R",
        "content": "Let's grow together!!1. RetweetUniversal recycling symbol2. Comment your YT/TwitchMovie camera#SmallStreamersConnect#SupportSmallStreamers #Twitchstream #TwitchFam @SupStreamers#twitchtv #SupportSmallStreams #SmallYouTubeArmy #twitchcommunity #logo #GFX #Twitch https://t.co/tyvveSfx2R",
        "like_count": 4,
        "comment_count": 1,
        "mediaUrl": [
            "https://pbs.twimg.com/media/FKMieUPWUAU4K8v.jpg"
        ]
    },
    {
        "idPost": "1811858005581005269",
        "urlPost": "pic.x.com/6iGINqy1Dj",
        "content": "\"I created this amazing Business logo design work for @prestigiousdukeIf you need an amazing logo or anything graphic, please get in touch with me.💜 https://t.co/6iGINqy1Dj",
        "like_count": 4,
        "comment_count": 0,
        "mediaUrl": [
            "https://pbs.twimg.com/media/GSUAoNgXwAE9crI.jpg"
        ]
    },
    {
        "idPost": "1490699155265794048",
        "urlPost": "pic.x.com/qHwYGLvY7r",
        "content": "Are you looking for 2d art? Does anybody need I'm here for you to serve best kindly HMU#needgraphicdesigner#needoverlay  #needanimation #needyoutubeintro #needemotes  #needNFT #SmallStreamersConnect#SupportSmallStreams#SupportSmallStreamers#100DaysOfCode@BlazedRTs https://t.co/qHwYGLvY7r",
        "like_count": 4,
        "comment_count": 0,
        "mediaUrl": [
            "https://pbs.twimg.com/media/FLAGTalWQAEqHQl.jpg"
        ]
    },
    {
        "idPost": "1570800596390940672",
        "urlPost": "pic.x.com/CNGSePcwyZ",
        "content": "Work done for my client.@Blvck_Spider😍Thank you for trusting me with your project.If you want anything feel free to contact me with your concept.#needgraphicdesigner#needoverlay  #needanimation #needemotes   #tattoodesign #bookcovers #needlogo #graphicsdesign #TwitterArt https://t.co/CNGSePcwyZ",
        "like_count": 3,
        "comment_count": 1,
        "mediaUrl": [
            "https://pbs.twimg.com/media/Fcya0RmWQAI1aMm.jpg"
        ]
    },
    {
        "idPost": "1504110766261256193",
        "urlPost": "pic.x.com/bpIdCKVkab",
        "content": "Does anybody need a cover art? I'm here for you to serve best kindly HMU!!#needgraphicdesigner#needoverlay  #needanimation #needyoutubeintro #needemotes  #needNFT #SmallStreamersConnect#SupportSmallStreams#SupportSmallStreamers#100DaysOfCode@BlazedRTs https://t.co/bpIdCKVkab",
        "like_count": 1,
        "comment_count": 0,
        "mediaUrl": [
            "https://pbs.twimg.com/media/FN-sxThXMAM3vUi.jpg"
        ]
    },
    {
        "idPost": "1575966605204332545",
        "urlPost": "pic.x.com/h01ho533oE",
        "content": "Another work done for my close client thank for trusting in me😍@Blvck_Spider for the consideration, people contact here for Dope quality Designing work  #graphicdesign#needoverlay  #needanimation #needemotes   #tattoodesign #bookcovers #needlogo #graphicsdesign #TwitterArt https://t.co/h01ho533oE",
        "like_count": 2,
        "comment_count": 0,
        "mediaUrl": [
            "https://pbs.twimg.com/media/Fd7015mWQBIw_8K.jpg"
        ]
    },
    {
        "idPost": "1716433174874685693",
        "urlPost": "pic.x.com/ewGWYgHksi",
        "content": "Yeyy! Guys, Halloween is almost here, so this month I'm giving a special commission reduction of 25%!So what are you waiting for? Send me a direct message if you need any kind of job!#animation #youtubepremium #twitch #commissionsopen #GraphicDesigner #Illustrator #ARTIST https://t.co/ewGWYgHksi",
        "like_count": 3,
        "comment_count": 0,
        "mediaUrl": [
            "https://pbs.twimg.com/media/F9H-lusa0AAOsR-.jpg"
        ]
    },
    {
        "idPost": "1487070157495226368",
        "urlPost": "pic.x.com/XXnliynVcr",
        "content": "Let's grow together!!1. RetweetUniversal recycling symbol2. Comment your YT/TwitchMovie camera#SmallStreamersConnect#SupportSmallStreamers #Twitchstream #TwitchFam @SupStreamers#twitchtv #SupportSmallStreams #SmallYouTubeArmy #twitchcommunity #logo #GFX #Twitch https://t.co/XXnliynVcr",
        "like_count": 3,
        "comment_count": 0,
        "mediaUrl": [
            "https://pbs.twimg.com/media/FKMibVIXwAANQV-.jpg"
        ]
    },
    {
        "idPost": "1633891722798284801",
        "urlPost": "pic.x.com/Vv3zTEHidh",
        "content": "Thank you so much @CinxDaPoet   for the consideration, people contact here for Dope quality Designing work #designer https://t.co/Vv3zTEHidh",
        "like_count": 2,
        "comment_count": 0,
        "mediaUrl": [
            "https://pbs.twimg.com/media/Fqy_0-qWwBs9X-V.jpg"
        ]
    }
]